smopay/__init__.py
smopay/card/__init__.py
smopay-0.0.10.dist-info/METADATA
smopay-0.0.10.dist-info/WHEEL
smopay-0.0.10.dist-info/top_level.txt
smopay-0.0.10.dist-info/RECORD
